instadm.py
instadm-0.0.2.dist-info/LICENSE
instadm-0.0.2.dist-info/METADATA
instadm-0.0.2.dist-info/WHEEL
instadm-0.0.2.dist-info/top_level.txt
instadm-0.0.2.dist-info/RECORD
