Metadata-Version: 2.1
Name: instadm
Version: 0.0.2
Summary: Instagram bot to send direct messages
Home-page: https://github.com/CamTosh/instagram-bot-dm
Author: Toche Camille
Author-email: tochecamille@gmail.com
License: GPLv3
Platform: UNKNOWN
Classifier: Intended Audience :: Developers
Classifier: Operating System :: OS Independent
Classifier: Topic :: Software Development
License-File: LICENSE
Requires-Dist: webdriver-manager
Requires-Dist: selenium
